whalesong/__init__.py
whalesong/driver.py
whalesong/driver_chromium.py
whalesong/driver_firefox.py
whalesong/errors.py
whalesong/firefox_profile.py
whalesong/models.py
whalesong/results.py
whalesong/firefox_profile_template/addons.json
whalesong/firefox_profile_template/containers.json
whalesong/firefox_profile_template/extensions.json
whalesong/firefox_profile_template/handlers.json
whalesong/firefox_profile_template/prefs.js
whalesong/firefox_profile_template/xulstore.json
whalesong/js/whalesong.js
whalesong/managers/__init__.py
whalesong/managers/chat.py
whalesong/managers/conn.py
whalesong/managers/contact.py
whalesong/managers/display_info.py
whalesong/managers/group_metadata.py
whalesong/managers/live_location.py
whalesong/managers/message.py
whalesong/managers/mute.py
whalesong/managers/presence.py
whalesong/managers/profile_pic_thumb.py
whalesong/managers/status.py
whalesong/managers/status_v3.py
whalesong/managers/sticker_pack.py
whalesong/managers/storage.py
whalesong/managers/stream.py
whalesong/managers/wap.py
whalesong-0.9.0.dist-info/METADATA
whalesong-0.9.0.dist-info/RECORD
whalesong-0.9.0.dist-info/WHEEL
whalesong-0.9.0.dist-info/top_level.txt
