Metadata-Version: 2.1
Name: whalesong
Version: 0.9.0
Summary: Whalesong is a python library to manage WebApps remotely. Currently WhatsappWeb is implemented
Home-page: https://github.com/alfred82santa/whalesong
Author: Alfred Santacatalina
Author-email: alfred82santa@gmail.com
License: MIT
Keywords: WebApp Selenium Web Whatsapp Chat Bot Chatbot
Platform: UNKNOWN
Classifier: Development Status :: 4 - Beta
Classifier: Intended Audience :: Developers
Classifier: Topic :: Communications :: Chat
Classifier: License :: OSI Approved :: MIT License
Classifier: Programming Language :: Python :: 3.6
Provides-Extra: chromium
Provides-Extra: firefox
Requires-Dist: dirty-models (>=0.11)
Requires-Dist: python-axolotl
Requires-Dist: cryptography
Requires-Dist: aiohttp (>=3.0)
Requires-Dist: vobject
Provides-Extra: chromium
Requires-Dist: pyppeteer; extra == 'chromium'
Requires-Dist: websockets (<7.0); extra == 'chromium'
Provides-Extra: firefox
Requires-Dist: selenium (>=3.4.3); extra == 'firefox'
